oogg/__init__.py
oogg/__main__.py
oogg/browser.py
oogg/error.py
oogg/main.py
oogg/provider.py
oogg/repository.py
oogg-1.1.1.dist-info/LICENSE
oogg-1.1.1.dist-info/METADATA
oogg-1.1.1.dist-info/WHEEL
oogg-1.1.1.dist-info/entry_points.txt
oogg-1.1.1.dist-info/top_level.txt
oogg-1.1.1.dist-info/RECORD
