Metadata-Version: 2.1
Name: oogg
Version: 1.1.1
Summary: Quick way to open files in GitHub and GitLab.
Home-page: https://github.com/r0x0d/oogg
Author: Rodolfo Olivieri
Author-email: rodolfo.olivieri3@gmail.com
License: MIT
Platform: UNKNOWN
Classifier: License :: OSI Approved :: MIT License
Classifier: Programming Language :: Python :: 3
Classifier: Programming Language :: Python :: 3 :: Only
Classifier: Programming Language :: Python :: 3.7
Classifier: Programming Language :: Python :: 3.8
Classifier: Programming Language :: Python :: 3.9
Classifier: Programming Language :: Python :: 3.10
Classifier: Programming Language :: Python :: Implementation :: CPython
Classifier: Programming Language :: Python :: Implementation :: PyPy
Requires-Python: >=3.7
License-File: LICENSE
Requires-Dist: giturlparse (>=0.10.0)
Requires-Dist: rich (>=11.2.0)
